libspitz/Args.py
libspitz/Blob.py
libspitz/ClientEndpoint.py
libspitz/Endpoint.py
libspitz/JobBinary.py
libspitz/Listener.py
libspitz/LogUtils.py
libspitz/PerfModule.py
libspitz/Pointer.py
libspitz/Result.py
libspitz/SimpleEndpoint.py
libspitz/TaskPool.py
libspitz/Timeout.py
libspitz/UIDUtils.py
libspitz/__init__.py
libspitz/memstat.py
libspitz/config/__init__.py
libspitz/messaging/MessagingError.py
libspitz/messaging/SocketClosed.py
libspitz/messaging/__init__.py
spitz-0.0.1.data/scripts/spitz-examples
spitz-0.0.1.data/scripts/spitz-gen-api
spitz-0.0.1.data/scripts/spitz-jm
spitz-0.0.1.data/scripts/spitz-tm
spitz-0.0.1.dist-info/LICENSE
spitz-0.0.1.dist-info/METADATA
spitz-0.0.1.dist-info/WHEEL
spitz-0.0.1.dist-info/top_level.txt
spitz-0.0.1.dist-info/RECORD
